{
  "id": "javascript",
  "name": "JavaScript",
  "title": "A JavaScript cheat sheet with the most important concepts, functions, methods, and more. A complete quick reference for beginners.",
  "icon": "https://raw.githubusercontent.com/Fechin/reference/main/source/assets/icon/javascript.svg",
  "sections": [
    {
      "id": "intro",
      "title": "Intro",
      "startIndex": 0
    },
    {
      "id": "s1",
      "title": "Getting Started",
      "startIndex": 1
    },
    {
      "id": "s2",
      "title": "JavaScript Conditionals",
      "startIndex": 13
    },
    {
      "id": "s3",
      "title": "JavaScript Functions",
      "startIndex": 28
    },
    {
      "id": "s4",
      "title": "JavaScript Scope",
      "startIndex": 44
    },
    {
      "id": "s5",
      "title": "JavaScript Arrays",
      "startIndex": 54
    },
    {
      "id": "s6",
      "title": "JavaScript Set",
      "startIndex": 68
    },
    {
      "id": "s7",
      "title": "JavaScript Loops",
      "startIndex": 75
    },
    {
      "id": "s8",
      "title": "JavaScript Iterators",
      "startIndex": 85
    },
    {
      "id": "s9",
      "title": "JavaScript Objects",
      "startIndex": 91
    },
    {
      "id": "s10",
      "title": "JavaScript Classes",
      "startIndex": 103
    },
    {
      "id": "s11",
      "title": "JavaScript Modules",
      "startIndex": 108
    },
    {
      "id": "s12",
      "title": "JavaScript Promises",
      "startIndex": 112
    },
    {
      "id": "s13",
      "title": "JavaScript Async-Await",
      "startIndex": 123
    },
    {
      "id": "s14",
      "title": "JavaScript Requests",
      "startIndex": 128
    }
  ],
  "cards": [
    {
      "id": "intro-0",
      "sectionId": "intro",
      "title": "Intro",
      "kind": "text",
      "body": "A JavaScript cheat sheet with the most important concepts, functions, methods, and more. A complete quick reference for beginners."
    },
    {
      "id": "s1-1",
      "sectionId": "s1",
      "title": "Introduction",
      "kind": "text",
      "body": "JavaScript is a lightweight, interpreted programming language."
    },
    {
      "id": "s1-2",
      "sectionId": "s1",
      "title": "Introduction",
      "kind": "text",
      "body": "• [JSON cheatsheet](/json) _(cheatsheets.zip)_\n• [Regex in JavaScript](/regex#regex-in-javascript) _(cheatsheets.zip)_"
    },
    {
      "id": "s1-3",
      "sectionId": "s1",
      "title": "Console",
      "kind": "code",
      "lang": "javascript",
      "code": "// => Hello world!\nconsole.log('Hello world!');\n\n// => Hello CheatSheets.zip\nconsole.warn('hello %s', 'CheatSheets.zip');\n\n// Prints error message to stderr\nconsole.error(new Error('Oops!'));"
    },
    {
      "id": "s1-4",
      "sectionId": "s1",
      "title": "Numbers",
      "kind": "code",
      "lang": "javascript",
      "code": "let amount = 6;\nlet price = 4.99;"
    },
    {
      "id": "s1-5",
      "sectionId": "s1",
      "title": "Variables",
      "kind": "code",
      "lang": "javascript",
      "code": "let x = null;\nlet name = 'Tammy';\nconst found = false;\n\n// => Tammy, false, null\nconsole.log(name, found, x);\n\nvar a;\nconsole.log(a); // => undefined"
    },
    {
      "id": "s1-6",
      "sectionId": "s1",
      "title": "Strings",
      "kind": "code",
      "lang": "javascript",
      "code": "let singleQuotes = 'Wheres my bandit hat?';\nlet doubleQuotes = 'Wheres my bandit hat?';\n// this is used to embed expressions or for creating multi-line strings\nlet backTicks = `Wheres my bandit hat? ${some_value}`;\n\n// they can also be mixed,\n// NOTE: if you need the functionality of the backticks, use it as the surrounding quotes\nlet mixedQuotes = `hello ${'dear' + name}, \"let's have a great day today`;\n\n// => 21\nconsole.log(singleQuotes.length);"
    },
    {
      "id": "s1-7",
      "sectionId": "s1",
      "title": "Arithmetic Operators",
      "kind": "code",
      "lang": "javascript",
      "code": "5 + 5 = 10     // Addition\n10 - 5 = 5     // Subtraction\n5 * 10 = 50    // Multiplication\n10 / 5 = 2     // Division\n10 % 5 = 0     // Modulo"
    },
    {
      "id": "s1-8",
      "sectionId": "s1",
      "title": "Comments",
      "kind": "code",
      "lang": "javascript",
      "code": "// This line will denote a comment\n\n/*\nThe below configuration must be\nchanged before deployment.\n*/"
    },
    {
      "id": "s1-9",
      "sectionId": "s1",
      "title": "Assignment Operators",
      "kind": "code",
      "lang": "javascript",
      "code": "let number = 100;\n\n// Both statements will add 10\nnumber = number + 10;\nnumber += 10;\n\nconsole.log(number);\n// => 120"
    },
    {
      "id": "s1-10",
      "sectionId": "s1",
      "title": "String Interpolation",
      "kind": "code",
      "lang": "javascript",
      "code": "let age = 7;\n\n// String concatenation\n'Tommy is ' + age + ' years old.';\n\n// String interpolation\n`Tommy is ${age} years old.`;"
    },
    {
      "id": "s1-11",
      "sectionId": "s1",
      "title": "let Keyword",
      "kind": "code",
      "lang": "javascript",
      "code": "let count;\nconsole.log(count); // => undefined\ncount = 10;\nconsole.log(count); // => 10"
    },
    {
      "id": "s1-12",
      "sectionId": "s1",
      "title": "const Keyword",
      "kind": "code",
      "lang": "javascript",
      "code": "const numberOfColumns = 4;\n\n// TypeError: Assignment to constant...\nnumberOfColumns = 8;"
    },
    {
      "id": "s2-13",
      "sectionId": "s2",
      "title": "if Statement",
      "kind": "code",
      "lang": "javascript",
      "code": "const isMailSent = true;\n\nif (isMailSent) {\n  console.log('Mail sent to recipient');\n}"
    },
    {
      "id": "s2-14",
      "sectionId": "s2",
      "title": "Ternary Operator",
      "kind": "code",
      "lang": "javascript",
      "code": "// The ternary operator is a concise way to write an if-else statement in a single line: condition ? exprIfTrue : exprIfFalse.\n\nvar x = 1;\n\n// true, (condition) ? value_if_true : value_if_false\nresult = x == 1 ? true : false;"
    },
    {
      "id": "s2-15",
      "sectionId": "s2",
      "title": "Operators",
      "kind": "code",
      "lang": "javascript",
      "code": "true || false; // true\n10 > 5 || 10 > 20; // true\nfalse || false; // false\n10 > 100 || 10 > 20; // false"
    },
    {
      "id": "s2-16",
      "sectionId": "s2",
      "title": "Operators",
      "kind": "text",
      "body": "#### Logical Operator &&"
    },
    {
      "id": "s2-17",
      "sectionId": "s2",
      "title": "Operators",
      "kind": "code",
      "lang": "javascript",
      "code": "true && true; // true\n1 > 2 && 2 > 1; // false\ntrue && false; // false\n4 === 4 && 3 > 1; // true"
    },
    {
      "id": "s2-18",
      "sectionId": "s2",
      "title": "Operators",
      "kind": "text",
      "body": "#### Comparison Operators"
    },
    {
      "id": "s2-19",
      "sectionId": "s2",
      "title": "Operators",
      "kind": "code",
      "lang": "javascript",
      "code": "1 > 3; // false\n3 > 1; // true\n250 >= 250; // true\n1 === 1; // true\n1 === 2; // false\n1 === '1'; // false"
    },
    {
      "id": "s2-20",
      "sectionId": "s2",
      "title": "Operators",
      "kind": "text",
      "body": "#### Logical Operator !"
    },
    {
      "id": "s2-21",
      "sectionId": "s2",
      "title": "Operators",
      "kind": "code",
      "lang": "javascript",
      "code": "let lateToWork = true;\nlet oppositeValue = !lateToWork;\n\n// => false\nconsole.log(oppositeValue);"
    },
    {
      "id": "s2-22",
      "sectionId": "s2",
      "title": "Operators",
      "kind": "text",
      "body": "#### Nullish coalescing operator ??"
    },
    {
      "id": "s2-23",
      "sectionId": "s2",
      "title": "Operators",
      "kind": "code",
      "lang": "javascript",
      "code": "null ?? 'I win'; //  'I win'\nundefined ?? 'Me too'; //  'Me too'\n\nfalse ?? 'I lose'; //  false\n0 ?? 'I lose again'; //  0\n'' ?? 'Damn it'; //  ''"
    },
    {
      "id": "s2-24",
      "sectionId": "s2",
      "title": "else if",
      "kind": "code",
      "lang": "javascript",
      "code": "const size = 10;\n\nif (size > 100) {\n  console.log('Big');\n} else if (size > 20) {\n  console.log('Medium');\n} else if (size > 4) {\n  console.log('Small');\n} else {\n  console.log('Tiny');\n}\n// Print: Small"
    },
    {
      "id": "s2-25",
      "sectionId": "s2",
      "title": "switch Statement",
      "kind": "code",
      "lang": "javascript",
      "code": "const food = 'salad';\n\nswitch (food) {\n  case 'oyster':\n    console.log('The taste of the sea');\n    break;\n  case 'pizza':\n    console.log('A delicious pie');\n    break;\n  default:\n    console.log('Enjoy your meal');\n}"
    },
    {
      "id": "s2-26",
      "sectionId": "s2",
      "title": "== vs ===",
      "kind": "code",
      "lang": "javascript",
      "code": "0 == false; // true\n0 === false; // false, different type\n1 == '1'; // true,  automatic type conversion\n1 === '1'; // false, different type\nnull == undefined; // true\nnull === undefined; // false\n'0' == false; // true\n'0' === false; // false"
    },
    {
      "id": "s2-27",
      "sectionId": "s2",
      "title": "== vs ===",
      "kind": "text",
      "body": "The `==` just check the value, `===` check both the value and the type."
    },
    {
      "id": "s3-28",
      "sectionId": "s3",
      "title": "Functions",
      "kind": "code",
      "lang": "javascript",
      "code": "// Defining the function:\nfunction sum(num1, num2) {\n  return num1 + num2;\n}\n\n// Calling the function:\nsum(3, 6); // 9"
    },
    {
      "id": "s3-29",
      "sectionId": "s3",
      "title": "Anonymous Functions",
      "kind": "code",
      "lang": "javascript",
      "code": "// Named function\nfunction rocketToMars() {\n  return 'BOOM!';\n}\n\n// Anonymous function\nconst rocketToMars = function () {\n  return 'BOOM!';\n};"
    },
    {
      "id": "s3-30",
      "sectionId": "s3",
      "title": "Arrow Functions (ES6)",
      "kind": "text",
      "body": "#### With two arguments"
    },
    {
      "id": "s3-31",
      "sectionId": "s3",
      "title": "Arrow Functions (ES6)",
      "kind": "code",
      "lang": "javascript",
      "code": "const sum = (param1, param2) => {\n  return param1 + param2;\n};\nconsole.log(sum(2, 5)); // => 7"
    },
    {
      "id": "s3-32",
      "sectionId": "s3",
      "title": "Arrow Functions (ES6)",
      "kind": "text",
      "body": "#### With no arguments"
    },
    {
      "id": "s3-33",
      "sectionId": "s3",
      "title": "Arrow Functions (ES6)",
      "kind": "code",
      "lang": "javascript",
      "code": "const printHello = () => {\n  console.log('hello');\n};\nprintHello(); // => hello"
    },
    {
      "id": "s3-34",
      "sectionId": "s3",
      "title": "Arrow Functions (ES6)",
      "kind": "text",
      "body": "#### With a single argument"
    },
    {
      "id": "s3-35",
      "sectionId": "s3",
      "title": "Arrow Functions (ES6)",
      "kind": "code",
      "lang": "javascript",
      "code": "const checkWeight = (weight) => {\n  console.log(`Weight : ${weight}`);\n};\ncheckWeight(25); // => Weight : 25"
    },
    {
      "id": "s3-36",
      "sectionId": "s3",
      "title": "Arrow Functions (ES6)",
      "kind": "text",
      "body": "#### Concise arrow functions"
    },
    {
      "id": "s3-37",
      "sectionId": "s3",
      "title": "Arrow Functions (ES6)",
      "kind": "code",
      "lang": "javascript",
      "code": "const multiply = (a, b) => a * b;\n// => 60\nconsole.log(multiply(2, 30));"
    },
    {
      "id": "s3-38",
      "sectionId": "s3",
      "title": "Arrow Functions (ES6)",
      "kind": "text",
      "body": "[Arrow function](https://developer.mozilla.org/en-US/docs/Web/JavaScript/Reference/Functions/Arrow_functions) available\nstarting ES2015"
    },
    {
      "id": "s3-39",
      "sectionId": "s3",
      "title": "return Keyword",
      "kind": "code",
      "lang": "javascript",
      "code": "// With return\nfunction sum(num1, num2) {\n  return num1 + num2;\n}\n\n// The function doesn't output the sum\nfunction sum(num1, num2) {\n  num1 + num2;\n}"
    },
    {
      "id": "s3-40",
      "sectionId": "s3",
      "title": "Calling Functions",
      "kind": "code",
      "lang": "javascript",
      "code": "// Defining the function\nfunction sum(num1, num2) {\n  return num1 + num2;\n}\n\n// Calling the function\nsum(2, 4); // 6"
    },
    {
      "id": "s3-41",
      "sectionId": "s3",
      "title": "Function Expressions",
      "kind": "code",
      "lang": "javascript",
      "code": "const dog = function () {\n  return 'Woof!';\n};"
    },
    {
      "id": "s3-42",
      "sectionId": "s3",
      "title": "Function Parameters",
      "kind": "code",
      "lang": "javascript",
      "code": "// The parameter is name\nfunction sayHello(name) {\n  return `Hello, ${name}!`;\n}"
    },
    {
      "id": "s3-43",
      "sectionId": "s3",
      "title": "Function Declaration",
      "kind": "code",
      "lang": "javascript",
      "code": "function add(num1, num2) {\n  return num1 + num2;\n}"
    },
    {
      "id": "s4-44",
      "sectionId": "s4",
      "title": "Scope",
      "kind": "code",
      "lang": "javascript",
      "code": "function myFunction() {\n  var pizzaName = 'Margarita';\n  // Code here can use pizzaName\n}\n\n// Code here can't use pizzaName"
    },
    {
      "id": "s4-45",
      "sectionId": "s4",
      "title": "Block Scoped Variables",
      "kind": "code",
      "lang": "javascript",
      "code": "const isLoggedIn = true;\n\nif (isLoggedIn == true) {\n  const statusMessage = 'Logged in.';\n}\n\n// Uncaught ReferenceError...\nconsole.log(statusMessage);"
    },
    {
      "id": "s4-46",
      "sectionId": "s4",
      "title": "Global Variables",
      "kind": "code",
      "lang": "javascript",
      "code": "// Variable declared globally\nconst color = 'blue';\n\nfunction printColor() {\n  console.log(color);\n}\n\nprintColor(); // => blue"
    },
    {
      "id": "s4-47",
      "sectionId": "s4",
      "title": "let vs var",
      "kind": "code",
      "lang": "javascript",
      "code": "for (let i = 0; i < 3; i++) {\n  // This is the Max Scope for 'let'\n  // i accessible ✔️\n}\n// i not accessible ❌"
    },
    {
      "id": "s4-48",
      "sectionId": "s4",
      "title": "let vs var",
      "kind": "text",
      "body": "---"
    },
    {
      "id": "s4-49",
      "sectionId": "s4",
      "title": "let vs var",
      "kind": "code",
      "lang": "javascript",
      "code": "for (var i = 0; i < 3; i++) {\n  // i accessible ✔️\n}\n// i accessible ✔️"
    },
    {
      "id": "s4-50",
      "sectionId": "s4",
      "title": "let vs var",
      "kind": "text",
      "body": "`var` is scoped to the nearest function block, and `let` is scoped to the nearest enclosing block."
    },
    {
      "id": "s4-51",
      "sectionId": "s4",
      "title": "Loops with closures",
      "kind": "text",
      "body": "```javascript{.wrap}\n// Prints 3 thrice, not what we meant.\nfor (var i = 0; i < 3; i++) {\nsetTimeout(_ => console.log(i), 10);\n}"
    },
    {
      "id": "s4-52",
      "sectionId": "s4",
      "title": "Loops with closures",
      "kind": "code",
      "lang": "",
      "code": "\n---\n\n```javascript{.wrap}\n// Prints 0, 1 and 2, as expected.\nfor (let j = 0; j < 3; j++) {\n  setTimeout(_ => console.log(j), 10);\n}"
    },
    {
      "id": "s4-53",
      "sectionId": "s4",
      "title": "Loops with closures",
      "kind": "text",
      "body": "The variable has its own copy using `let`, and the variable has shared copy using `var`."
    },
    {
      "id": "s5-54",
      "sectionId": "s5",
      "title": "Arrays",
      "kind": "code",
      "lang": "javascript",
      "code": "const fruits = ['apple', 'orange', 'banana'];\n\n// Different data types\nconst data = [1, 'chicken', false];"
    },
    {
      "id": "s5-55",
      "sectionId": "s5",
      "title": "Property .length",
      "kind": "code",
      "lang": "javascript",
      "code": "const numbers = [1, 2, 3, 4];\n\nnumbers.length; // 4"
    },
    {
      "id": "s5-56",
      "sectionId": "s5",
      "title": "Index",
      "kind": "code",
      "lang": "javascript",
      "code": "// Accessing an array element\nconst myArray = [100, 200, 300];\n\nconsole.log(myArray[0]); // 100\nconsole.log(myArray[1]); // 200"
    },
    {
      "id": "s5-57",
      "sectionId": "s5",
      "title": "Mutable chart",
      "kind": "text",
      "body": "|           | add | remove | start | end |\n| :-------- | :-: | :----: | :---: | :-: |\n| `push`    | ✔  |        |       | ✔  |\n| `pop`     |     |   ✔   |       | ✔  |\n| `unshift` | ✔  |        |  ✔   |     |\n| `shift`   |     |   ✔   |  ✔   |     |"
    },
    {
      "id": "s5-58",
      "sectionId": "s5",
      "title": "Array.push()",
      "kind": "code",
      "lang": "javascript",
      "code": "// Adding a single element:\nconst cart = ['apple', 'orange'];\ncart.push('pear');\n\n// Adding multiple elements:\nconst numbers = [1, 2];\nnumbers.push(3, 4, 5);"
    },
    {
      "id": "s5-59",
      "sectionId": "s5",
      "title": "Array.push()",
      "kind": "text",
      "body": "Add items to the end and returns the new array length."
    },
    {
      "id": "s5-60",
      "sectionId": "s5",
      "title": "Array.pop()",
      "kind": "code",
      "lang": "javascript",
      "code": "const fruits = ['apple', 'orange', 'banana'];\n\nconst fruit = fruits.pop(); // 'banana'\nconsole.log(fruits); // [\"apple\", \"orange\"]"
    },
    {
      "id": "s5-61",
      "sectionId": "s5",
      "title": "Array.pop()",
      "kind": "text",
      "body": "Remove an item from the end and returns the removed item."
    },
    {
      "id": "s5-62",
      "sectionId": "s5",
      "title": "Array.shift()",
      "kind": "code",
      "lang": "javascript",
      "code": "let cats = ['Bob', 'Willy', 'Mini'];\n\ncats.shift(); // ['Willy', 'Mini']"
    },
    {
      "id": "s5-63",
      "sectionId": "s5",
      "title": "Array.shift()",
      "kind": "text",
      "body": "Remove an item from the beginning and returns the removed item."
    },
    {
      "id": "s5-64",
      "sectionId": "s5",
      "title": "Array.unshift()",
      "kind": "code",
      "lang": "javascript",
      "code": "let cats = ['Bob'];\n\n// => ['Willy', 'Bob']\ncats.unshift('Willy');\n\n// => ['Puff', 'George', 'Willy', 'Bob']\ncats.unshift('Puff', 'George');"
    },
    {
      "id": "s5-65",
      "sectionId": "s5",
      "title": "Array.unshift()",
      "kind": "text",
      "body": "Add items to the beginning and returns the new array length."
    },
    {
      "id": "s5-66",
      "sectionId": "s5",
      "title": "Array.concat()",
      "kind": "code",
      "lang": "javascript",
      "code": "const numbers = [3, 2, 1];\nconst newFirstNumber = 4;\n\n// => [ 4, 3, 2, 1 ]\n[newFirstNumber].concat(numbers);\n\n// => [ 3, 2, 1, 4 ]\nnumbers.concat(newFirstNumber);"
    },
    {
      "id": "s5-67",
      "sectionId": "s5",
      "title": "Array.concat()",
      "kind": "text",
      "body": "If you want to avoid mutating your original array, you can use concat."
    },
    {
      "id": "s6-68",
      "sectionId": "s6",
      "title": "Create Set",
      "kind": "code",
      "lang": "javascript",
      "code": "// Empty Set Object\nconst emptySet = new Set();\n\n// Set Object with values\nconst setObj = new Set([1, true, 'hi']);"
    },
    {
      "id": "s6-69",
      "sectionId": "s6",
      "title": "Add",
      "kind": "code",
      "lang": "javascript",
      "code": "const emptySet = new Set();\n\n// add values\nemptySet.add('a'); // 'a'\nemptySet.add(1); // 'a', 1\nemptySet.add(true); // 'a', 1, true\nemptySet.add('a'); // 'a', 1, true"
    },
    {
      "id": "s6-70",
      "sectionId": "s6",
      "title": "Delete",
      "kind": "code",
      "lang": "javascript",
      "code": "const emptySet = new Set([1, true, 'a']);\n\n// delete values\nemptySet.delete('a'); // 1, true\nemptySet.delete(true); // 1\nemptySet.delete(1); //"
    },
    {
      "id": "s6-71",
      "sectionId": "s6",
      "title": "Has",
      "kind": "code",
      "lang": "javascript",
      "code": "const setObj = new Set([1, true, 'a']);\n\n// returns true or false\nsetObj.has('a'); // true\nsetObj.has(1); // true\nsetObj.has(false); // false"
    },
    {
      "id": "s6-72",
      "sectionId": "s6",
      "title": "Clear",
      "kind": "code",
      "lang": "javascript",
      "code": "const setObj = new Set([1, true, 'a']);\n\n// clears the set\nconsole.log(setObj); // 1, true, 'a'\nsetObj.clear(); //"
    },
    {
      "id": "s6-73",
      "sectionId": "s6",
      "title": "Size",
      "kind": "code",
      "lang": "javascript",
      "code": "const setObj = new Set([1, true, 'a']);\n\nconsoloe.log(setObj.size); // 3"
    },
    {
      "id": "s6-74",
      "sectionId": "s6",
      "title": "ForEach",
      "kind": "code",
      "lang": "javascript",
      "code": "const setObj = new Set([1, true, 'a']);\n\nsetObj.forEach(function (value) {\n  console.log(value);\n});\n\n// 1\n// true\n// 'a'"
    },
    {
      "id": "s7-75",
      "sectionId": "s7",
      "title": "While Loop",
      "kind": "code",
      "lang": "javascript",
      "code": "while (condition) {\n  // code block to be executed\n}\n\nlet i = 0;\nwhile (i < 5) {\n  console.log(i);\n  i++;\n}"
    },
    {
      "id": "s7-76",
      "sectionId": "s7",
      "title": "Reverse Loop",
      "kind": "code",
      "lang": "javascript",
      "code": "const fruits = ['apple', 'orange', 'banana'];\n\nfor (let i = fruits.length - 1; i >= 0; i--) {\n  console.log(`${i}. ${fruits[i]}`);\n}\n\n// => 2. banana\n// => 1. orange\n// => 0. apple"
    },
    {
      "id": "s7-77",
      "sectionId": "s7",
      "title": "Do…While Statement",
      "kind": "code",
      "lang": "javascript",
      "code": "x = 0;\ni = 0;\n\ndo {\n  x = x + i;\n  console.log(x);\n  i++;\n} while (i < 5);\n// => 0 1 3 6 10"
    },
    {
      "id": "s7-78",
      "sectionId": "s7",
      "title": "For Loop",
      "kind": "code",
      "lang": "javascript",
      "code": "for (let i = 0; i < 4; i += 1) {\n  console.log(i);\n}\n\n// => 0, 1, 2, 3"
    },
    {
      "id": "s7-79",
      "sectionId": "s7",
      "title": "Looping Through Arrays",
      "kind": "code",
      "lang": "javascript",
      "code": "for (let i = 0; i < array.length; i++) {\n  console.log(array[i]);\n}\n\n// => Every item in the array"
    },
    {
      "id": "s7-80",
      "sectionId": "s7",
      "title": "Break",
      "kind": "code",
      "lang": "javascript",
      "code": "for (let i = 0; i < 99; i += 1) {\n  if (i > 5) {\n    break;\n  }\n  console.log(i);\n}\n// => 0 1 2 3 4 5"
    },
    {
      "id": "s7-81",
      "sectionId": "s7",
      "title": "Continue",
      "kind": "code",
      "lang": "javascript",
      "code": "for (i = 0; i < 10; i++) {\n  if (i === 3) {\n    continue;\n  }\n  text += 'The number is ' + i + '<br>';\n}"
    },
    {
      "id": "s7-82",
      "sectionId": "s7",
      "title": "Nested",
      "kind": "code",
      "lang": "javascript",
      "code": "for (let i = 0; i < 2; i += 1) {\n  for (let j = 0; j < 3; j += 1) {\n    console.log(`${i}-${j}`);\n  }\n}"
    },
    {
      "id": "s7-83",
      "sectionId": "s7",
      "title": "for...in loop",
      "kind": "code",
      "lang": "javascript",
      "code": "const fruits = ['apple', 'orange', 'banana'];\n\n// 1. Print only indexes\nfor (let index in fruits) {\n  console.log(index);\n}\n// => 0\n// => 1\n// => 2\n\n\n// 2. Print only values\nfor (let index in fruits) {\n  console.log(fruits[index]);\n}\n// => apple\n// => orange\n// => banana\n\n\n// 3. Print index with value\nfor (let index in fruits) {\n  console.log(index, fruits[index]);\n}\n// => 0 apple\n// => 1 orange\n// => 2 banana"
    },
    {
      "id": "s7-84",
      "sectionId": "s7",
      "title": "for...of loop",
      "kind": "code",
      "lang": "javascript",
      "code": "const fruits = ['apple', 'orange', 'banana'];\n\nfor (let fruit of fruits) {\n  console.log(fruit);\n}\n// => apple\n// => orange\n// => banana\n\nfor (let [index, value] of fruits.entries()) {\n  console.log(index, value);\n}\n// => 0 apple\n// => 1 orange\n// => 2 banana"
    },
    {
      "id": "s8-85",
      "sectionId": "s8",
      "title": "Functions Assigned to Variables",
      "kind": "code",
      "lang": "javascript",
      "code": "let plusFive = (number) => {\n  return number + 5;\n};\n// f is assigned the value of plusFive\nlet f = plusFive;\n\nplusFive(3); // 8\n// Since f has a function value, it can be invoked.\nf(9); // 14"
    },
    {
      "id": "s8-86",
      "sectionId": "s8",
      "title": "Callback Functions",
      "kind": "code",
      "lang": "javascript",
      "code": "const isEven = (n) => {\n  return n % 2 == 0;\n};\n\nlet printMsg = (evenFunc, num) => {\n  const isNumEven = evenFunc(num);\n  console.log(`${num} is an even number: ${isNumEven}.`);\n};\n\n// Pass in isEven as the callback function\nprintMsg(isEven, 4);\n// => 4 is an even number: True."
    },
    {
      "id": "s8-87",
      "sectionId": "s8",
      "title": "Array.reduce()",
      "kind": "code",
      "lang": "javascript",
      "code": "const numbers = [1, 2, 3, 4];\n\nconst sum = numbers.reduce((accumulator, curVal) => {\n  return accumulator + curVal;\n});\n\nconsole.log(sum); // 10"
    },
    {
      "id": "s8-88",
      "sectionId": "s8",
      "title": "Array.map()",
      "kind": "code",
      "lang": "javascript",
      "code": "const members = ['Taylor', 'Donald', 'Don', 'Natasha', 'Bobby'];\n\nconst announcements = members.map((member) => {\n  return member + ' joined the contest.';\n});\n\nconsole.log(announcements);"
    },
    {
      "id": "s8-89",
      "sectionId": "s8",
      "title": "Array.forEach()",
      "kind": "code",
      "lang": "javascript",
      "code": "const numbers = [28, 77, 45, 99, 27];\n\nnumbers.forEach((number) => {\n  console.log(number);\n});"
    },
    {
      "id": "s8-90",
      "sectionId": "s8",
      "title": "Array.filter()",
      "kind": "code",
      "lang": "javascript",
      "code": "const randomNumbers = [4, 11, 42, 14, 39];\nconst filteredArray = randomNumbers.filter((n) => {\n  return n > 5;\n});"
    },
    {
      "id": "s9-91",
      "sectionId": "s9",
      "title": "Accessing Properties",
      "kind": "code",
      "lang": "javascript",
      "code": "const apple = {\n  color: 'Green',\n  price: { bulk: '$3/kg', smallQty: '$4/kg' }\n};\nconsole.log(apple.color); // => Green\nconsole.log(apple.price.bulk); // => $3/kg"
    },
    {
      "id": "s9-92",
      "sectionId": "s9",
      "title": "Naming Properties",
      "kind": "code",
      "lang": "javascript",
      "code": "// Example of invalid key names\nconst trainSchedule = {\n  // Invalid because of the space between words.\n  platform num: 10,\n  // Expressions cannot be keys.\n  40 - 10 + 2: 30,\n  // A + sign is invalid unless it is enclosed in quotations.\n  +compartment: 'C'\n}"
    },
    {
      "id": "s9-93",
      "sectionId": "s9",
      "title": "Non-existent properties",
      "kind": "code",
      "lang": "javascript",
      "code": "const classElection = {\n  date: 'January 12'\n};\n\nconsole.log(classElection.place); // undefined"
    },
    {
      "id": "s9-94",
      "sectionId": "s9",
      "title": "Mutable",
      "kind": "code",
      "lang": "javascript",
      "code": "const student = {\n  name: 'Sheldon',\n  score: 100,\n  grade: 'A'\n};\n\nconsole.log(student);\n// { name: 'Sheldon', score: 100, grade: 'A' }\n\ndelete student.score;\nstudent.grade = 'F';\nconsole.log(student);\n// { name: 'Sheldon', grade: 'F' }\n\nstudent = {};\n// TypeError: Assignment to constant variable."
    },
    {
      "id": "s9-95",
      "sectionId": "s9",
      "title": "Assignment shorthand syntax",
      "kind": "code",
      "lang": "javascript",
      "code": "const person = {\n  name: 'Tom',\n  age: '22'\n};\nconst { name, age } = person;\nconsole.log(name); // 'Tom'\nconsole.log(age); // '22'"
    },
    {
      "id": "s9-96",
      "sectionId": "s9",
      "title": "Delete operator",
      "kind": "code",
      "lang": "javascript",
      "code": "const person = {\n  firstName: 'Matilda',\n  age: 27,\n  hobby: 'knitting',\n  goal: 'learning JavaScript'\n};\n\ndelete person.hobby; // or delete person[hobby];\n\nconsole.log(person);\n/*\n{\n  firstName: \"Matilda\"\n  age: 27\n  goal: \"learning JavaScript\"\n}\n*/"
    },
    {
      "id": "s9-97",
      "sectionId": "s9",
      "title": "Objects as arguments",
      "kind": "code",
      "lang": "javascript",
      "code": "const origNum = 8;\nconst origObj = { color: 'blue' };\n\nconst changeItUp = (num, obj) => {\n  num = 7;\n  obj.color = 'red';\n};\n\nchangeItUp(origNum, origObj);\n\n// Will output 8 since integers are passed by value.\nconsole.log(origNum);\n\n// Will output 'red' since objects are passed\n// by reference and are therefore mutable.\nconsole.log(origObj.color);"
    },
    {
      "id": "s9-98",
      "sectionId": "s9",
      "title": "Shorthand object creation",
      "kind": "code",
      "lang": "javascript",
      "code": "const activity = 'Surfing';\nconst beach = { activity };\nconsole.log(beach); // { activity: 'Surfing' }"
    },
    {
      "id": "s9-99",
      "sectionId": "s9",
      "title": "this Keyword",
      "kind": "code",
      "lang": "javascript",
      "code": "const cat = {\n  name: 'Pipey',\n  age: 8,\n  whatName() {\n    return this.name;\n  }\n};\nconsole.log(cat.whatName()); // => Pipey"
    },
    {
      "id": "s9-100",
      "sectionId": "s9",
      "title": "Factory functions",
      "kind": "code",
      "lang": "javascript",
      "code": "// A factory function that accepts 'name',\n// 'age', and 'breed' parameters to return\n// a customized dog object.\nconst dogFactory = (name, age, breed) => {\n  return {\n    name: name,\n    age: age,\n    breed: breed,\n    bark() {\n      console.log('Woof!');\n    }\n  };\n};"
    },
    {
      "id": "s9-101",
      "sectionId": "s9",
      "title": "Object methods",
      "kind": "code",
      "lang": "javascript",
      "code": "const engine = {\n  // method shorthand, with one argument\n  start(adverb) {\n    console.log(`The engine starts up ${adverb}...`);\n  },\n  // anonymous arrow function expression with no arguments\n  sputter: () => {\n    console.log('The engine sputters...');\n  }\n};\n\nengine.start('noisily');\nengine.sputter();"
    },
    {
      "id": "s9-102",
      "sectionId": "s9",
      "title": "Getters and setters",
      "kind": "code",
      "lang": "javascript",
      "code": "const myCat = {\n  _name: 'Dottie',\n  get name() {\n    return this._name;\n  },\n  set name(newName) {\n    this._name = newName;\n  }\n};\n\n// Reference invokes the getter\nconsole.log(myCat.name);\n\n// Assignment invokes the setter\nmyCat.name = 'Yankee';"
    },
    {
      "id": "s10-103",
      "sectionId": "s10",
      "title": "Static Methods",
      "kind": "code",
      "lang": "javascript",
      "code": "class Dog {\n  constructor(name) {\n    this._name = name;\n  }\n\n  introduce() {\n    console.log('This is ' + this._name + ' !');\n  }\n\n  // A static method\n  static bark() {\n    console.log('Woof!');\n  }\n}\n\nconst myDog = new Dog('Buster');\nmyDog.introduce();\n\n// Calling the static method\nDog.bark();"
    },
    {
      "id": "s10-104",
      "sectionId": "s10",
      "title": "Class",
      "kind": "code",
      "lang": "javascript",
      "code": "class Song {\n  constructor() {\n    this.title;\n    this.author;\n  }\n\n  play() {\n    console.log('Song playing!');\n  }\n}\n\nconst mySong = new Song();\nmySong.play();"
    },
    {
      "id": "s10-105",
      "sectionId": "s10",
      "title": "Class Constructor",
      "kind": "code",
      "lang": "javascript",
      "code": "class Song {\n  constructor(title, artist) {\n    this.title = title;\n    this.artist = artist;\n  }\n}\n\nconst mySong = new Song('Bohemian Rhapsody', 'Queen');\nconsole.log(mySong.title);"
    },
    {
      "id": "s10-106",
      "sectionId": "s10",
      "title": "Class Methods",
      "kind": "code",
      "lang": "javascript",
      "code": "class Song {\n  play() {\n    console.log('Playing!');\n  }\n\n  stop() {\n    console.log('Stopping!');\n  }\n}"
    },
    {
      "id": "s10-107",
      "sectionId": "s10",
      "title": "extends",
      "kind": "code",
      "lang": "javascript",
      "code": "// Parent class\nclass Media {\n  constructor(info) {\n    this.publishDate = info.publishDate;\n    this.name = info.name;\n  }\n}\n\n// Child class\nclass Song extends Media {\n  constructor(songData) {\n    super(songData);\n    this.artist = songData.artist;\n  }\n}\n\nconst mySong = new Song({\n  artist: 'Queen',\n  name: 'Bohemian Rhapsody',\n  publishDate: 1975\n});"
    },
    {
      "id": "s11-108",
      "sectionId": "s11",
      "title": "Export",
      "kind": "code",
      "lang": "javascript",
      "code": "// myMath.js\n\n// Default export\nexport default function add(x, y) {\n  return x + y;\n}\n\n// Normal export\nexport function subtract(x, y) {\n  return x - y;\n}\n\n// Multiple exports\nfunction multiply(x, y) {\n  return x * y;\n}\nfunction duplicate(x) {\n  return x * 2;\n}\nexport { multiply, duplicate };"
    },
    {
      "id": "s11-109",
      "sectionId": "s11",
      "title": "Import",
      "kind": "code",
      "lang": "javascript",
      "code": "// main.js\nimport add, { subtract, multiply, duplicate } from './myMath.js';\n\nconsole.log(add(6, 2)); // 8\nconsole.log(subtract(6, 2)) // 4\nconsole.log(multiply(6, 2)); // 12\nconsole.log(duplicate(5)) // 10\n\n// index.html\n<script type=\"module\" src=\"main.js\"></script>"
    },
    {
      "id": "s11-110",
      "sectionId": "s11",
      "title": "Export Module",
      "kind": "code",
      "lang": "javascript",
      "code": "// myMath.js\n\nfunction add(x, y) {\n  return x + y;\n}\nfunction subtract(x, y) {\n  return x - y;\n}\nfunction multiply(x, y) {\n  return x * y;\n}\nfunction duplicate(x) {\n  return x * 2;\n}\n\n// Multiple exports in node.js\nmodule.exports = {\n  add,\n  subtract,\n  multiply,\n  duplicate\n};"
    },
    {
      "id": "s11-111",
      "sectionId": "s11",
      "title": "Require Module",
      "kind": "code",
      "lang": "javascript",
      "code": "// main.js\nconst myMath = require('./myMath.js');\n\nconsole.log(myMath.add(6, 2)); // 8\nconsole.log(myMath.subtract(6, 2)); // 4\nconsole.log(myMath.multiply(6, 2)); // 12\nconsole.log(myMath.duplicate(5)); // 10"
    },
    {
      "id": "s12-112",
      "sectionId": "s12",
      "title": "Promise states",
      "kind": "code",
      "lang": "javascript",
      "code": "const promise = new Promise((resolve, reject) => {\n  const res = true;\n  // An asynchronous operation.\n  if (res) {\n    resolve('Resolved!');\n  } else {\n    reject(Error('Error'));\n  }\n});\n\npromise.then(\n  (res) => console.log(res),\n  (err) => console.error(err)\n);"
    },
    {
      "id": "s12-113",
      "sectionId": "s12",
      "title": "Executor function",
      "kind": "code",
      "lang": "javascript",
      "code": "const executorFn = (resolve, reject) => {\n  resolve('Resolved!');\n};\n\nconst promise = new Promise(executorFn);"
    },
    {
      "id": "s12-114",
      "sectionId": "s12",
      "title": "setTimeout()",
      "kind": "code",
      "lang": "javascript",
      "code": "const loginAlert = () => {\n  console.log('Login');\n};\n\nsetTimeout(loginAlert, 6000);"
    },
    {
      "id": "s12-115",
      "sectionId": "s12",
      "title": ".then() method",
      "kind": "code",
      "lang": "javascript",
      "code": "const promise = new Promise((resolve, reject) => {\n  setTimeout(() => {\n    resolve('Result');\n  }, 200);\n});\n\npromise.then(\n  (res) => {\n    console.log(res);\n  },\n  (err) => {\n    console.error(err);\n  }\n);"
    },
    {
      "id": "s12-116",
      "sectionId": "s12",
      "title": "Promise.catch()",
      "kind": "code",
      "lang": "javascript",
      "code": "const promise = new Promise((resolve, reject) => {\n  setTimeout(() => {\n    reject(Error('Promise Rejected Unconditionally.'));\n  }, 1000);\n});\n\npromise.then((res) => {\n  console.log(value);\n});\n\npromise.catch((err) => {\n  console.error(err);\n});"
    },
    {
      "id": "s12-117",
      "sectionId": "s12",
      "title": "Promise.all()",
      "kind": "code",
      "lang": "javascript",
      "code": "const promise1 = new Promise((resolve, reject) => {\n  setTimeout(() => {\n    resolve(3);\n  }, 300);\n});\nconst promise2 = new Promise((resolve, reject) => {\n  setTimeout(() => {\n    resolve(2);\n  }, 200);\n});\n\nPromise.all([promise1, promise2]).then((res) => {\n  console.log(res[0]);\n  console.log(res[1]);\n});"
    },
    {
      "id": "s12-118",
      "sectionId": "s12",
      "title": "Promise.allSettled()",
      "kind": "code",
      "lang": "javascript",
      "code": "const promise1 = Promise.resolve(3);\nconst promise2 = new Promise((resolve, reject) => {\n  setTimeout(() => {\n    reject(2);\n  }, 100);\n});\n\nPromise.allSettled([promise1, promise2]).then((res) => {\n  console.log(res[0].status);\n  console.log(res[1].status);\n});"
    },
    {
      "id": "s12-119",
      "sectionId": "s12",
      "title": "Avoiding nested Promise and .then()",
      "kind": "code",
      "lang": "javascript",
      "code": "const promise = new Promise((resolve, reject) => {\n  setTimeout(() => {\n    resolve('*');\n  }, 1000);\n});\n\nconst twoStars = (star) => {\n  return star + star;\n};\n\nconst oneDot = (star) => {\n  return star + '.';\n};\n\nconst print = (val) => {\n  console.log(val);\n};\n\n// Chaining them all together\npromise.then(twoStars).then(oneDot).then(print);"
    },
    {
      "id": "s12-120",
      "sectionId": "s12",
      "title": "Creating",
      "kind": "code",
      "lang": "javascript",
      "code": "const executorFn = (resolve, reject) => {\n  console.log('The executor function of the promise!');\n};\n\nconst promise = new Promise(executorFn);"
    },
    {
      "id": "s12-121",
      "sectionId": "s12",
      "title": "Chaining multiple .then()",
      "kind": "code",
      "lang": "javascript",
      "code": "const promise = new Promise((resolve) =>\n  setTimeout(() => resolve('dAlan'), 100)\n);\n\npromise\n  .then((res) => {\n    return res === 'Alan'\n      ? Promise.resolve('Hey Alan!')\n      : Promise.reject('Who are you?');\n  })\n  .then(\n    (res) => {\n      console.log(res);\n    },\n    (err) => {\n      console.error(err);\n    }\n  );"
    },
    {
      "id": "s12-122",
      "sectionId": "s12",
      "title": "Fake http Request with Promise",
      "kind": "code",
      "lang": "javascript",
      "code": "const mock = (success, timeout = 1000) => {\n  return new Promise((resolve, reject) => {\n    setTimeout(() => {\n      if (success) {\n        resolve({ status: 200, data: {} });\n      } else {\n        reject({ message: 'Error' });\n      }\n    }, timeout);\n  });\n};\nconst someEvent = async () => {\n  try {\n    await mock(true, 1000);\n  } catch (e) {\n    console.log(e.message);\n  }\n};"
    },
    {
      "id": "s13-123",
      "sectionId": "s13",
      "title": "Asynchronous",
      "kind": "code",
      "lang": "javascript",
      "code": "function helloWorld() {\n  return new Promise((resolve) => {\n    setTimeout(() => {\n      resolve('Hello World!');\n    }, 2000);\n  });\n}\n\nconst msg = async function () {\n  //Async Function Expression\n  const msg = await helloWorld();\n  console.log('Message:', msg);\n};\n\nconst msg1 = async () => {\n  //Async Arrow Function\n  const msg = await helloWorld();\n  console.log('Message:', msg);\n};\n\nmsg(); // Message: Hello World! <-- after 2 seconds\nmsg1(); // Message: Hello World! <-- after 2 seconds"
    },
    {
      "id": "s13-124",
      "sectionId": "s13",
      "title": "Resolving Promises",
      "kind": "code",
      "lang": "javascript",
      "code": "let pro1 = Promise.resolve(5);\nlet pro2 = 44;\nlet pro3 = new Promise(function (resolve, reject) {\n  setTimeout(resolve, 100, 'foo');\n});\n\nPromise.all([pro1, pro2, pro3]).then(function (values) {\n  console.log(values);\n});\n// expected => Array [5, 44, \"foo\"]"
    },
    {
      "id": "s13-125",
      "sectionId": "s13",
      "title": "Async Await Promises",
      "kind": "code",
      "lang": "javascript",
      "code": "function helloWorld() {\n  return new Promise((resolve) => {\n    setTimeout(() => {\n      resolve('Hello World!');\n    }, 2000);\n  });\n}\n\nasync function msg() {\n  const msg = await helloWorld();\n  console.log('Message:', msg);\n}\n\nmsg(); // Message: Hello World! <-- after 2 seconds"
    },
    {
      "id": "s13-126",
      "sectionId": "s13",
      "title": "Error Handling",
      "kind": "code",
      "lang": "javascript",
      "code": "let json = '{ \"age\": 30 }'; // incomplete data\n\ntry {\n  let user = JSON.parse(json); // <-- no errors\n  console.log(user.name); // no name!\n} catch (e) {\n  console.error('Invalid JSON data!');\n}"
    },
    {
      "id": "s13-127",
      "sectionId": "s13",
      "title": "Aysnc await operator",
      "kind": "code",
      "lang": "javascript",
      "code": "function helloWorld() {\n  return new Promise((resolve) => {\n    setTimeout(() => {\n      resolve('Hello World!');\n    }, 2000);\n  });\n}\n\nasync function msg() {\n  const msg = await helloWorld();\n  console.log('Message:', msg);\n}\n\nmsg(); // Message: Hello World! <-- after 2 seconds"
    },
    {
      "id": "s14-128",
      "sectionId": "s14",
      "title": "JSON",
      "kind": "code",
      "lang": "json",
      "code": "const jsonObj = {\n  \"name\": \"Rick\",\n  \"id\": \"11A\",\n  \"level\": 4\n};"
    },
    {
      "id": "s14-129",
      "sectionId": "s14",
      "title": "JSON",
      "kind": "text",
      "body": "Also see: [JSON cheatsheet](/json)"
    },
    {
      "id": "s14-130",
      "sectionId": "s14",
      "title": "XMLHttpRequest",
      "kind": "code",
      "lang": "javascript",
      "code": "const xhr = new XMLHttpRequest();\nxhr.open('GET', 'mysite.com/getjson');"
    },
    {
      "id": "s14-131",
      "sectionId": "s14",
      "title": "XMLHttpRequest",
      "kind": "text",
      "body": "`XMLHttpRequest` is a browser-level API that enables the client to script data transfers via JavaScript, NOT part of the\nJavaScript language."
    },
    {
      "id": "s14-132",
      "sectionId": "s14",
      "title": "GET",
      "kind": "code",
      "lang": "javascript",
      "code": "const req = new XMLHttpRequest();\nreq.responseType = 'json';\nreq.open('GET', '/getdata?id=65');\nreq.onload = () => {\n  console.log(xhr.response);\n};\n\nreq.send();"
    },
    {
      "id": "s14-133",
      "sectionId": "s14",
      "title": "POST",
      "kind": "code",
      "lang": "javascript",
      "code": "const data = {\n  fish: 'Salmon',\n  weight: '1.5 KG',\n  units: 5\n};\nconst xhr = new XMLHttpRequest();\nxhr.open('POST', '/inventory/add');\nxhr.responseType = 'json';\nxhr.send(JSON.stringify(data));\n\nxhr.onload = () => {\n  console.log(xhr.response);\n};"
    },
    {
      "id": "s14-134",
      "sectionId": "s14",
      "title": "fetch api",
      "kind": "code",
      "lang": "javascript",
      "code": "fetch(url, {\n    method: 'POST',\n    headers: {\n      'Content-type': 'application/json',\n      'apikey': apiKey\n    },\n    body: data\n  }).then(response => {\n    if (response.ok) {\n      return response.json();\n    }\n    throw new Error('Request failed!');\n  }, networkError => {\n    console.log(networkError.message)\n  })\n}"
    },
    {
      "id": "s14-135",
      "sectionId": "s14",
      "title": "JSON Formatted",
      "kind": "code",
      "lang": "javascript",
      "code": "fetch('url-that-returns-JSON')\n  .then((response) => response.json())\n  .then((jsonResponse) => {\n    console.log(jsonResponse);\n  });"
    },
    {
      "id": "s14-136",
      "sectionId": "s14",
      "title": "promise url parameter fetch api",
      "kind": "code",
      "lang": "javascript",
      "code": "fetch('url')\n.then(\n  response  => {\n    console.log(response);\n  },\n rejection => {\n    console.error(rejection.message);\n);"
    },
    {
      "id": "s14-137",
      "sectionId": "s14",
      "title": "Fetch API Function",
      "kind": "code",
      "lang": "javascript",
      "code": "fetch('https://api-xxx.com/endpoint', {\n  method: 'POST',\n  body: JSON.stringify({ id: '200' })\n})\n  .then(\n    (response) => {\n      if (response.ok) {\n        return response.json();\n      }\n      throw new Error('Request failed!');\n    },\n    (networkError) => {\n      console.log(networkError.message);\n    }\n  )\n  .then((jsonResponse) => {\n    console.log(jsonResponse);\n  });"
    },
    {
      "id": "s14-138",
      "sectionId": "s14",
      "title": "async await syntax",
      "kind": "code",
      "lang": "javascript",
      "code": "const getSuggestions = async () => {\n  const wordQuery = inputField.value;\n  const endpoint = `${url}${queryParams}${wordQuery}`;\n  try {\n    const response = await fetch(endpoint, { cache: 'no-cache' });\n    if (response.ok) {\n      const jsonResponse = await response.json();\n    }\n  } catch (error) {\n    console.log(error);\n  }\n};"
    }
  ],
  "source": {
    "repo": "https://github.com/Fechin/reference",
    "path": "source/_posts/javascript.md",
    "ref": "main",
    "url": "https://github.com/Fechin/reference/tree/main/source/_posts/javascript.md",
    "lang": "en",
    "mode": "local"
  }
}