{
  "id": "kanbanmail",
  "name": "KanbanMail",
  "title": "A visual cheat-sheet for the 29 keyboard shortcuts found in KanbanMail",
  "icon": "https://raw.githubusercontent.com/Fechin/reference/main/source/assets/icon/kanbanmail.svg",
  "sections": [
    {
      "id": "intro",
      "title": "Intro",
      "startIndex": 0
    },
    {
      "id": "s1",
      "title": "Keyboard Shortcuts",
      "startIndex": 1
    },
    {
      "id": "s2",
      "title": "Also see",
      "startIndex": 6
    }
  ],
  "cards": [
    {
      "id": "intro-0",
      "sectionId": "intro",
      "title": "Intro",
      "kind": "text",
      "body": "A visual cheat-sheet for the 29 keyboard shortcuts found in KanbanMail"
    },
    {
      "id": "s1-1",
      "sectionId": "s1",
      "title": "Global",
      "kind": "text",
      "body": "| Shortcut   | Action            |\n| ---------- | ----------------- |\n| `Ctrl` `\\` | Toggle split view |"
    },
    {
      "id": "s1-2",
      "sectionId": "s1",
      "title": "Board",
      "kind": "text",
      "body": "| Shortcut   | Action                                       |\n| ---------- | -------------------------------------------- |\n| `C`        | Open composer                                |\n| `Ctrl` `N` | New note in the to-do column                 |\n| `/`        | Focus the search bar                         |\n| `Esc`      | Clear search, if it's on                     |\n| `1-5`      | Select the first thread in column \\<number\\> |"
    },
    {
      "id": "s1-3",
      "sectionId": "s1",
      "title": "Email",
      "kind": "text",
      "body": "| Shortcut    | Action                                   |\n| ----------- | ---------------------------------------- |\n| `S`         | Star or unstar                           |\n| `I`         | Mark as important or not important       |\n| `U`         | Mark as read or unread                   |\n| `Shift` `P` | Pin                                      |\n| `R`         | Reply                                    |\n| `A`         | Reply all                                |\n| `F`         | Forward                                  |\n| `E`         | Move to archived                         |\n| `1-5`       | Move to column \\<number\\>                |\n| `Shift` `3` | Move to trash                            |\n| `P`         | Go to the previous message in the thread |\n| `N`         | Go to the next message in the thread     |\n| `Shift` `U` | Unsubscribe                              |\n| `Enter`     | Open selected thread                     |\n| `Esc`       | Close thread viewer, if open             |\n| `Esc`       | Clear selected threads                   |"
    },
    {
      "id": "s1-4",
      "sectionId": "s1",
      "title": "Composer",
      "kind": "text",
      "body": "| Shortcut       | Action         |\n| -------------- | -------------- |\n| `Ctrl` `Enter` | Send email     |\n| `Ctrl` `S`     | Save as draft  |\n| `Esc`          | Close composer |"
    },
    {
      "id": "s1-5",
      "sectionId": "s1",
      "title": "Editor",
      "kind": "text",
      "body": "| Shortcut   | Action        |\n| ---------- | ------------- |\n| `Ctrl` `B` | Bold          |\n| `Ctrl` `I` | Italic        |\n| `Ctrl` `U` | Underline     |\n| `Ctrl` `K` | Add hyperlink |"
    },
    {
      "id": "s2-6",
      "sectionId": "s2",
      "title": "Also see",
      "kind": "text",
      "body": "• [Keyboard shortcuts for KanbanMail](https://guides.kanbanmail.app/keyboard-shortcuts) _(guides.kanbanmail.app)_"
    }
  ],
  "source": {
    "repo": "https://github.com/Fechin/reference",
    "path": "source/_posts/kanbanmail.md",
    "ref": "main",
    "url": "https://github.com/Fechin/reference/tree/main/source/_posts/kanbanmail.md",
    "lang": "en",
    "mode": "local"
  }
}