{
  "id": "soundcloud",
  "name": "SoundCloud",
  "title": "A visual cheat-sheet for the 22 keyboard shortcuts found on SoundCloud",
  "icon": "https://raw.githubusercontent.com/Fechin/reference/main/source/assets/icon/soundcloud.svg",
  "sections": [
    {
      "id": "intro",
      "title": "Intro",
      "startIndex": 0
    },
    {
      "id": "s1",
      "title": "Keyboard Shortcuts",
      "startIndex": 1
    },
    {
      "id": "s2",
      "title": "Also see",
      "startIndex": 23
    }
  ],
  "cards": [
    {
      "id": "intro-0",
      "sectionId": "intro",
      "title": "Intro",
      "kind": "text",
      "body": "A visual cheat-sheet for the 22 keyboard shortcuts found on SoundCloud"
    },
    {
      "id": "s1-1",
      "sectionId": "s1",
      "title": "General I",
      "kind": "qa",
      "front": "`Space`",
      "back": "Play or pause"
    },
    {
      "id": "s1-2",
      "sectionId": "s1",
      "title": "General I",
      "kind": "qa",
      "front": "`Shift` `Right`",
      "back": "Play next track"
    },
    {
      "id": "s1-3",
      "sectionId": "s1",
      "title": "General I",
      "kind": "qa",
      "front": "`Shift` `L`",
      "back": "Repeat playing track"
    },
    {
      "id": "s1-4",
      "sectionId": "s1",
      "title": "General I",
      "kind": "qa",
      "front": "`Shift` `Left`",
      "back": "Play previous track"
    },
    {
      "id": "s1-5",
      "sectionId": "s1",
      "title": "General I",
      "kind": "qa",
      "front": "`Right`",
      "back": "Seek forward"
    },
    {
      "id": "s1-6",
      "sectionId": "s1",
      "title": "General I",
      "kind": "qa",
      "front": "`L`",
      "back": "Like playing track"
    },
    {
      "id": "s1-7",
      "sectionId": "s1",
      "title": "General I",
      "kind": "qa",
      "front": "`R`",
      "back": "Repost playing track"
    },
    {
      "id": "s1-8",
      "sectionId": "s1",
      "title": "General I",
      "kind": "qa",
      "front": "`S`",
      "back": "Search"
    },
    {
      "id": "s1-9",
      "sectionId": "s1",
      "title": "General I",
      "kind": "qa",
      "front": "`G` `L`",
      "back": "Navigate to likes"
    },
    {
      "id": "s1-10",
      "sectionId": "s1",
      "title": "General I",
      "kind": "qa",
      "front": "`G` `C`",
      "back": "Navigate to library"
    },
    {
      "id": "s1-11",
      "sectionId": "s1",
      "title": "General II",
      "kind": "qa",
      "front": "`G` `H`",
      "back": "Navigate to history"
    },
    {
      "id": "s1-12",
      "sectionId": "s1",
      "title": "General II",
      "kind": "qa",
      "front": "`Shift` `S`",
      "back": "Shuffle"
    },
    {
      "id": "s1-13",
      "sectionId": "s1",
      "title": "General II",
      "kind": "qa",
      "front": "`Shift` `Down`",
      "back": "Decrease volume"
    },
    {
      "id": "s1-14",
      "sectionId": "s1",
      "title": "General II",
      "kind": "qa",
      "front": "`Shift` `Up`",
      "back": "Increase volume"
    },
    {
      "id": "s1-15",
      "sectionId": "s1",
      "title": "General II",
      "kind": "qa",
      "front": "`M`",
      "back": "Mute volume"
    },
    {
      "id": "s1-16",
      "sectionId": "s1",
      "title": "General II",
      "kind": "qa",
      "front": "`Left`",
      "back": "Seek backwards"
    },
    {
      "id": "s1-17",
      "sectionId": "s1",
      "title": "General II",
      "kind": "qa",
      "front": "`0-9`",
      "back": "Seek to position"
    },
    {
      "id": "s1-18",
      "sectionId": "s1",
      "title": "General II",
      "kind": "qa",
      "front": "`P`",
      "back": "Navigate to playing track"
    },
    {
      "id": "s1-19",
      "sectionId": "s1",
      "title": "General II",
      "kind": "qa",
      "front": "`H`",
      "back": "Show keyboard shortcuts"
    },
    {
      "id": "s1-20",
      "sectionId": "s1",
      "title": "General II",
      "kind": "qa",
      "front": "`G` `S`",
      "back": "Navigate to stream"
    },
    {
      "id": "s1-21",
      "sectionId": "s1",
      "title": "General II",
      "kind": "qa",
      "front": "`G` `P`",
      "back": "Navigate to profile"
    },
    {
      "id": "s1-22",
      "sectionId": "s1",
      "title": "General II",
      "kind": "qa",
      "front": "`Q`",
      "back": "Show next up"
    },
    {
      "id": "s2-23",
      "sectionId": "s2",
      "title": "Also see",
      "kind": "text",
      "body": "• [Keyboard shortcuts for SoundCloud](https://i.imgur.com/ZQf24je.png) _(i.imgur.com)_"
    }
  ],
  "source": {
    "repo": "https://github.com/Fechin/reference",
    "path": "source/_posts/soundcloud.md",
    "ref": "main",
    "url": "https://github.com/Fechin/reference/tree/main/source/_posts/soundcloud.md",
    "lang": "en",
    "mode": "local"
  }
}