{
  "id": "symbol-code",
  "name": "Symbol Code 备忘清单",
  "title": "这份速查表是 Symbol 特殊符号列表",
  "icon": "https://raw.githubusercontent.com/jaywcjlove/reference/main/assets/symbol-code.svg",
  "sections": [
    {
      "id": "intro",
      "title": "简介",
      "startIndex": 0
    },
    {
      "id": "s1",
      "title": "Symbol 特殊符号",
      "startIndex": 1
    },
    {
      "id": "s2",
      "title": "图形符号",
      "startIndex": 20
    },
    {
      "id": "s3",
      "title": "人物符号",
      "startIndex": 30
    },
    {
      "id": "s4",
      "title": "数学符号",
      "startIndex": 35
    },
    {
      "id": "s5",
      "title": "语言符号",
      "startIndex": 41
    },
    {
      "id": "s6",
      "title": "另见",
      "startIndex": 55
    }
  ],
  "cards": [
    {
      "id": "intro-0",
      "sectionId": "intro",
      "title": "简介",
      "body": "这份速查表是 Symbol 特殊符号列表"
    },
    {
      "id": "s1-1",
      "sectionId": "s1",
      "title": "热门符号",
      "body": "```\nღ • ⁂ € ™ ↑ → ↓ ⇝ √ ∞ ░ ▲ ▶ ◀ ● ☀ ☁ ☂ ☃ ☄ ★ ☆ ☉ ☐ ☑ ☎ ☚ ☛ ☜ ☝ ☞ ☟ ☠ ☢ ☣ ☪ ☮ ☯ ☸ ☹ ☺ ☻ ☼ ☽ ☾ ♔ ♕ ♖ ♗ ♘ ♚ ♛ ♜ ♝ ♞ ♟ ♡♨ ♩ ♪ ♫ ♬ ✈ ✉ ✍ ✎ ✓ ✔ ✘ ✚ ✞ ✟ ✠ ✡ ✦ ✧ ✩✪ ✮ ✯ ✹ ✿ ❀ ❁ ❂ ❄ ❅ ❆ ❝ ❞ ❣ ❤ ❥ ❦ ➤\n```"
    },
    {
      "id": "s1-2",
      "sectionId": "s1",
      "title": "特殊符号 - 国际象棋符号列表视图",
      "body": "```\n♔ ♕ ♖ ♗ ♘ ♙ ♚ ♛ ♜ ♝ ♞ ♟\n```"
    },
    {
      "id": "s1-3",
      "sectionId": "s1",
      "title": "音符符号",
      "body": "```\n♩ ♪ ♫ ♬ ♭ ♮ ♯ 𝄞 𝄡 𝄢 𝄪 𝄫 🎵 🎶 🎼 𓏢 \n```"
    },
    {
      "id": "s1-4",
      "sectionId": "s1",
      "title": "天气符号",
      "body": "```\nϟ ☀ ☁ ☂ ☃ ☄ ☉ ☼ ☽ ☾ ♁ ♨ ❄ ❅ ❆ ༄ ࿓\n```"
    },
    {
      "id": "s1-5",
      "sectionId": "s1",
      "title": "办公室的符号",
      "body": "```\n‱ № ℗ ℠ ℡ ℻ ℀ ℁ ℅ ℆ ⅍ ⌚ ⌛ ☊ ☎ ☏ ✁ ✂ ✃ ✄ ✆ ✇ ✈ ✉ ✍ ✎ ✏ ✐ ✑✒ ™ © ® ‰ § ¶ 𓍝\n```"
    },
    {
      "id": "s1-6",
      "sectionId": "s1",
      "title": "技术符号",
      "body": "```\n⏎ ⇧ ⏏ ⌂ ⌘☢ ☣ ⎋ ⌥ ⌫ ᵁ ᴴ ᴰ ⌖  \n```"
    },
    {
      "id": "s1-7",
      "sectionId": "s1",
      "title": "菜单",
      "body": "```\n☰ ≡ Ξ ㊂ ≣ ⁝ ⋮ ︙ ⦙ ⁞ ⋯ … ∷ ▲ ▼ ▶ △ ▽ ▷ ⌃ ⌄ ︿ ﹀ ︽ ︾ ⌵ 𓏬 𓃑 𓏧 ⸬\n```"
    },
    {
      "id": "s1-8",
      "sectionId": "s1",
      "title": "星座符号",
      "body": "```\n♓ ♒ ♑ ♐ ♏ ♎ ♍ ♌ ♋ ♊ ♉ ♈ ☉ ☽ ☿ ♀ ⊕ ♁ ♂ ♃ ♄ ♅ ⛢ ♆ ♇\n```"
    },
    {
      "id": "s1-9",
      "sectionId": "s1",
      "title": "打勾符号",
      "body": "```\n✓ ✔ ✖ ✗ ✘ ∛ ∜ ⍻ ☐ ☑ ☒ □ ■ ○ ● ༝ ྾ ∨ 🆅 🆇 🅥 🅧 ⊗ \n```"
    },
    {
      "id": "s1-10",
      "sectionId": "s1",
      "title": "扑克符号",
      "body": "```\n♡ ♢ ♤ ♧ ♣ ♦ ♥ ♠\n```"
    },
    {
      "id": "s1-11",
      "sectionId": "s1",
      "title": "骰子符号",
      "body": "```\n⚀ ⚁ ⚂ ⚃ ⚄ ⚅ \n```"
    },
    {
      "id": "s1-12",
      "sectionId": "s1",
      "title": "键盘符号",
      "body": "• `⌘` command\n• `⌥` otptin\n• `⎋` escap\n• `⌫` backspace\n• `⌦` delete\n• `↑` up\n• `→` right\n• `←` left\n• `↓` down\n• `⇥` tab\n• `⇧` shift\n• `⇪` capslock\n• `⌃` control\n• `⏎` reternkey"
    },
    {
      "id": "s1-13",
      "sectionId": "s1",
      "title": "爱心符号",
      "body": "```\n♡ ♥ ❣ ❤ ❦ ❧ ❥ ☙ დ ღ\n```"
    },
    {
      "id": "s1-14",
      "sectionId": "s1",
      "title": "动物符号",
      "body": "```\n𓃥 𓃠 𓃰 𓃱 𓃯 𓃭 𓃸 𓃵 𓃗 𓃘 𓃙 𓃟 𓄀 𓄁 𓄂 𓄃 𓃚 𓃛 𓃜 𓃝 𓃞 𓃒 𓃓 𓃔 𓃕 𓃖 𓃡 𓃢 𓃦 𓃩 𓃫 𓃬 𓃮 𓃲 𓃴 𓃶 𓃷 𓃹 𓃻 𓃽 𓃾 𓃿 𓄄 𓄅 𓄆 𓄇 𓆇 𓆈 𓆉 𓆌 𓆏 𓆗 𓆘 𓆙 𓆚 𓆐 𓆑 𓆒 𓆓 𓆔 𓆕 𓆖 𓆊 𓆍 𓆣 𓆤 𓆥 𓆦 𓆧 𓆨 𓆛 𓆜 𓆝 𓆞 𓆟 𓆠 𓆡 𓆢 𓄿 𓅀 𓅁 𓅂 𓅃 𓅄 𓅅 𓅆 𓅇 𓅈 𓅉 𓅊 𓅋 𓅌 𓅍 𓅎 𓅏𓅐 𓅑 𓅒 𓅓 𓅔 𓅕𓅖 𓅗 𓅘 𓅙𓅚 𓅛 𓅜 𓅝 𓅞 𓅟 𓅠 𓅡 𓅢 𓅣 𓅤 𓅥 𓅦 𓅧 𓅨 𓅩 𓅪 𓅫 𓅬 𓅭 𓅮 𓅯 𓅰 𓅱 𓅲 𓅳 𓅴 𓅵 𓅶 𓅷 𓅸 𓅹 𓅺 𓅻 𓅼 𓅽 𓅾 𓅿 𓆀 𓆁 𓆂 𓆃 𓆆\n```"
    },
    {
      "id": "s1-15",
      "sectionId": "s1",
      "title": "星号符号 - 天空中的星星",
      "body": "```\n★ ☆ ✡ ✦ ✧ ⌑ ✩ ✪ ⍟ ❂ ✫ ✬ ✭ ✮ ✯ ✰ ☪ ⍣ ⋆ ≛ 𓇼 𓇻 𓇽 ꙳ ⭑ ⭒ 𖤐\n```"
    },
    {
      "id": "s1-16",
      "sectionId": "s1",
      "title": "星号符号",
      "body": "```\n* ∗ ٭ ※ ⁂ ⁎ ⁑ ⁕⃰ ⊛ ☸ ❋ ✱ ✲ ✳ ✴ ✵ ✶ ✷ ✸ ✹ ✺ ✽ ⧆ ＊ ﹡ ＊ † ‡\n```"
    },
    {
      "id": "s1-17",
      "sectionId": "s1",
      "title": "箭头符号",
      "body": "```\n↕ ↖ ↗ ↘ ↙ ↚ ↛ ↜ ↝ ↞ ↟ ↠ ↡ ↢ ↣ ↤ ↥ ↦ ↧ ↨ ↩ ↪ ↫ ↬ ↭ ↮ ↯ ↰ ↱ ↲ ↳ ↴ ↶ ↷ ↸ ↹ ↺ ↻ ⟳ ↼ ↽ ↾ ↿ ⇀ ⇁ ⇂ ⇃ ⇄ ⇅ ⇆ ⇇ ⇈ ⇉ ⇊ ⇋ ⇌ ⇍ ⇎ ⇏ ⇕ ⇖ ⇗ ⇘ ⇙ ⇚ ⇛ ⇜ ⇝ ⇞ ⇟ ⇠ ⇡ ⇢ ⇣ ⇤ ⇥ ⇦ ⇧ ⇨ ⇩ ⇪ ⌅ ⌆ ⌤ ⏎ ▶ ☇ ☈ ➔ ➘ ➙ ➚ ➛ ➜ ➝ ➞ ➟ ➠ ➡ ➢ ➣ ➤ ➥ ➦ ➧ ➨ ➩ ➪ ➫ ➬ ➭ ➮ ➯ ➱ ➲ ➳ ➴ ➵ ➶ ➷ ➸ ➹ ➺ ➻ ➼ ➽ ➾ ⤴ ⤵ ↵ ↓ ↔ ← → ↑ ⍇ ⍈ ⍐ ⍗ ⇫ ⇬ ⇭ ⇮ ⇯ ⇰ ⇱ ⇲ ⇳ ⇴ ⇵ ⇶ ⇷ ⇸ ⇹ ⇺ ⇻ ⇼ ⇽ ⇾ ⇿ ⇐ ⇑ ⇒ ⇓ ⇔\n```"
    },
    {
      "id": "s1-18",
      "sectionId": "s1",
      "title": "货币符号",
      "body": "```\n$ ¢ € £ ¥ ₩ ₽ ₹ ¤ ₱ ₦ ƒ ₮ ৲ ৳ ₨ ௹ ฿ ៛ ₪ ₫ ₭ ₲ ₴ ₵ ﷼ ≋ ₿ Ł Ð ₳\n```"
    },
    {
      "id": "s1-19",
      "sectionId": "s1",
      "title": "花卉符号",
      "body": "```\n✻ ✼ ✾ ✿ ❀ ❁ ❃ ❇ ❈ ❉ ❊ ✢ ✣ ✤ ✥ ꕥ 𓇬 ⚘ 𓆸 𓆹 𓆼 𓇊 𓇚 𓇕 𓇗 𓋇 𓁙 𓁋 ֍ ֎ 𓆭 𓆰 𓆱 𓇋𓇑 𓇛 𓇟 𓇣꧁ ꧂ \n```"
    },
    {
      "id": "s2-20",
      "sectionId": "s2",
      "title": "方形符号",
      "body": "```\n∎ ⊞ ⊟ ⊠ ⊡ ⋄ ⎔ ⎚ ▀ ▁ ▂ ▃ ▄ ▅ ▆ ▇ █ ▉ ▊ ▋ ▋ ▌▍ ▎ ▏ ▐ ░ ▒ ▓ ▔ ■ □ ▢▣ ▤ ▥ ▦ ▧ ▨ ▩ ▪  ▫ ▬ ▭ ▮ ▯ ▰ ▱ ◆ ◇ ◈ ◘ ◙ ◚ ◛ ◧ ◨ ◩ ◪ ◫ ☖ ☗ ⭔ ⭓ ❏ ❐ ❑ ❒ ❖ ❘ ❙ ❚ ◊ ⌑ ▖ ▗ ▘ ▙ ▚ ▛ ▜ ▝ ▞ ▟ ◰ ◱ ◲ ◳\n```"
    },
    {
      "id": "s2-21",
      "sectionId": "s2",
      "title": "三角形符号",
      "body": "```\n⊿ ▲ △ ▴ ▵ ▶ ▷ ▸ ▹ ► ▻ ▼ ▽ ▾ ▿ ◀ ◁ ◂ ◃ ◄ ◅ ◢ ◣ ◤ ◥ ◬ ◭ ◮ ◸ ◹ ◺ ◿ ∇ ∆\n```"
    },
    {
      "id": "s2-22",
      "sectionId": "s2",
      "title": "线段符号",
      "body": "```\nˍ ‐ ⎯ ‒ ― ─ ━ │ ┃ ┄ ┅ ┆ ┇ ┈ ┉ ┊ ┋ ╌ ╍ ╎ ╴ ╵ ╶ ╷ ╸ ╹ ╺ ╻ ╼ ╽ ╾ ╿ ▏ ▕ ╏ – — ⌜ ⌝ ⌞ ⌟ ┌ ┍ ┎ ┏ ┐ ┑ ┒ ┓ └ ┕ ┖ ┗ ┘ ┙ ┚ ┛ ├ ┝ ┞ ┟ ┠ ┡ ┢ ┣ ┤ ┥ ┦ ┧ ┨ ┩ ┪ ┫ ┬ ┭ ┮ ┯ ┰ ┱ ┲ ┳ ┴ ┵ ┶ ┷ ┸ ┹ ┺ ┻ ┼ ┽ ┾ ┿ ╀ ╁ ╂ ╃ ╄ ╅ ╆ ╇ ╈ ╉ ╊ ╋ ═ ║ ╒ ╓ ╔ ╕ ╖ ╗ ╘ ╙ ╚ ╛ ╜ ╝ ╞ ╟ ╠ ╡ ╢ ╣ ╤ ╥ ╦ ╧ ╨ ╩ ╪ ╫ ╬ ╱ ╲ ╳ ╭ ╮ ╯ ╰ ◜ ◝ ◞ ◟ ◠ ◡ ⌈ ⌊ ⌉ ⌋ ⎛ ⎝ ⎞ ⎠ ⎡ ⎣ ⎤ ⎦ ⎧ ⎩ ⎫ ⎭ ⎸ ⎹ ⎾ ⎿ ⏉ ⏊ ⏋ ⏌ ≡ ≣ ☰ ☱ ☲ ☳ ☴ ☵ ☶ ☷\n```"
    },
    {
      "id": "s2-23",
      "sectionId": "s2",
      "title": "圆形符号",
      "body": "```\n⊖ ⊘ ⊙ ⊚ ⊛ ⊜ ⊝ ◉ ○ ◌ ◍ ◎ ● ◐ ◑ ◒ ◓ ◔ ◕ ◖ ◗ ◦ ◯ ◴ ◵ ◶ ◷ ❍ ₒ ॰ ° ৹ ๐ º 𐤏 Ｏ ⦿ ⊕ ⊗ ⨷ ⭕ 🅞 Ⓞ ⓞ\n```"
    },
    {
      "id": "s2-24",
      "sectionId": "s2",
      "title": "X 标记符号",
      "body": "```\n× ☓ ✕ ✖ ❌ ❎ ⨉ ⨯ ☐ ☒ ✗ ✘ Χ χ ꭓ ᚷ ⊗ ⨷ ₓ ˣ\n```"
    },
    {
      "id": "s2-25",
      "sectionId": "s2",
      "title": "项目清单",
      "body": "```\n• · ∙ ⊙ ⊚ ⊛ ◉ ○ ◌ ◍ ◎ ● ◘ ◦ 。 ☉ ⦾ ⦿ ⁃ ⁌ ⁍ ◆ ◇ ◈ ★ ☆ ■ □ ☐ ☑ ☒ ✓ ✔ ❖ ⋄ ❥ ❧ ☙ ☸ ✤ ✱ ✲ ✦ ✧ ↠ ↣ ↦ ↬ ⇛ ⇝ ⇢ ⇨ ➔ ➙ ➛ ➜ ➝ ➞ ➟ ➠ ➡ ➢ ➣ ➤ ➥ ➦ ➧ ➨ ➮ ➱ ➲ ➳ ➵ ➸ ➼ ➽ ➾ → ⇾ ⇒ ‣ ▶ ▷ ▸ ▹ ► ▻\n```"
    },
    {
      "id": "s2-26",
      "sectionId": "s2",
      "title": "盲文符号",
      "body": "```\n⣿ ⠿ ⠾ ⠽ ⠼ ⠻ ⠺ ⠹ ⠸ ⠷ ⠶ ⠵ ⠴ ⠳ ⠲ ⠱ ⠰ ⠯ ⠮ ⠭ ⠬ ⠫ ⠪ ⠩ ⠨ ⠧ ⠦ ⠥ ⠤ ⠣ ⠢ ⠡ ⠠ ⠟ ⠞ ⠝ ⠜ ⠛ ⠚ ⠙ ⠘ ⠗ ⠖ ⠕ ⠔ ⠓ ⠒ ⠑ ⠐ ⠏ ⠎ ⠍ ⠌ ⠋ ⠊ ⠉ ⠈ ⠇ ⠆ ⠅⠄ ⠃ ⠂ ⠁ ⠀ \n```"
    },
    {
      "id": "s2-27",
      "sectionId": "s2",
      "title": "麻将符号",
      "body": "```\n🀀  🀄︎  🀁  🀂  🀃  🀅  🀆  🀇  🀈  🀉  🀊  🀋  🀌  🀍  🀎  🀏  🀐  🀑  🀒  🀓  🀔  🀕  🀖  🀗  🀘  🀙  🀚  🀛  🀜  🀝  🀞  🀟  🀠  🀡  🀢  🀣  🀤  🀥  🀦  🀧  🀨  🀩  \n```"
    },
    {
      "id": "s2-28",
      "sectionId": "s2",
      "title": "制表符",
      "body": "```\n┏┳┓   ╔╦╗   ╓╥╖  ┌┬┐ \n┣╋┫   ╠╬╣   ╟╫╢  ├┼┤\n┗┻┛   ╚╩╝   ╙╨╜  └┴┘\n╭╮  ╱╲  ━━ ══ ┅┅ ┈┈\n╰╯  ╲╱  ﹍  ﹎﹉  ﹊\n_  ＿  ﹏  ˉ  ￣  ﹌  ˇ\n╳ ¦  ‖ ︴ ︳| ┃ ║ ┆ ┇\n```"
    },
    {
      "id": "s2-29",
      "sectionId": "s2",
      "title": "表格",
      "body": "```\n┏━━┳━━┓╔══╦══╗┌┈┈┬┈┈┐\n┣━━╋━━┫║  ║  ║├┈┈┼┈┈┤\n┃  ┃  ┃╠══╬══╣┆  ┆  ┆\n┗━━┻━━┛╚══╩══╝└┈┈┴┈┈┘\n  ╭┈┈┬┈┈╮\n  ├┈┈┼┈┈┤\n  ├┈┈┼┈┈┤\n  ╰┈┈┴┈┈╯\n```"
    },
    {
      "id": "s3-30",
      "sectionId": "s3",
      "title": "人员和活动",
      "body": "```\n𓀞 𓀟 𓀠 𓀡 𓀢 𓀣 𓀤 𓀥 𓀦 𓀧 𓀨 𓀩 𓀪 𓀫 𓀬 𓀀 𓀁 𓀂 𓀃 𓀄 𓀅 𓀆 𓀇 𓀈 𓀉 𓀊 𓀋 𓀌 𓀍 𓀎 𓀏 𓀑 𓀒 𓀓 𓀔 𓀕 𓀖 𓀗 𓀘 𓀙 𓀚 𓀛 𓀜 𓀝 𓁁 𓁂 𓁃 𓁄 𓁅 𓁆 𓁇 𓁈 𓁉 𓁊 𓁋 𓁌 𓁍 𓁎 𓁏 𓁐 𓁑 𓁒 𓁓 𓁔 𓁕 𓁖 𓁗 𓁘 𓁙 𓀭 𓀮 𓀯 𓀰 𓀱 𓀲 𓀳 𓀴 𓀵 𓀶 𓀷 𓀸 𓀹 𓀺 𓀻 𓀼 𓀽 𓀾 𓀿 𓁀 𓁲 𓁚 𓁛 𓁜 𓁝 𓁞 𓁟 𓁠 𓁡 𓁢 𓁣 𓁤 𓁥 𓁦 𓁧 𓁨 𓁩 𓁪 𓁫 𓁬 𓁭 𓁮 𓁯 𓁰 𓁱 𓁳 𓁴 𓁵\n```"
    },
    {
      "id": "s3-31",
      "sectionId": "s3",
      "title": "脸和笑脸符号",
      "body": "```\n☹ ☺ ☻ ☿ ♀ ⚣ ⚤ ⚥ ⚦ ⚧  ⚨ ♂ ⚢ 〠 ヅ ツ ㋡ 웃 유 ü ت ⍢ ⍨ ⚇ ⚉ 𓁷 𓁶 𓂈 𓂉 𓂊 𓂎 𓂀 𓁿 𓁾 𓁽 𓁼 𓁻 𓁺 𓁹\n```"
    },
    {
      "id": "s3-32",
      "sectionId": "s3",
      "title": "心形符号",
      "body": "```\n♡ ♥ ❣ ❤ ❦ ❧ ❥ ☙ დ ღ\n```"
    },
    {
      "id": "s3-33",
      "sectionId": "s3",
      "title": "手符号",
      "body": "```\n☚ ☛ ☜ ☝ ☞ ☟ ✌ ✍ 𓂬 𓂩 𓂨 𓂷 𓂭𓂝 𓂡 𓂦 𓃈 ⍝\n```"
    },
    {
      "id": "s3-34",
      "sectionId": "s3",
      "title": "文化符号",
      "body": "```\n☠ ⚰ ☤ ☥ ☦ ☧ ☨ ☩ ☪ ☫ ☬ ☮☭ ☯ ☸ ☽ ☾ ✙ ✚ ✛ ✜ ✝ ✞✟ ✠ ✡ 卍 ﷽\n```"
    },
    {
      "id": "s4-35",
      "sectionId": "s4",
      "title": "计数符号",
      "body": "```\n∟ ∬ ∭ ∮ ∵ ∷ ≦ ≧ ≋ ╳ ✕ ✖ ✚ ﹢ ﹣ ﹤ ﹥ ％ ＋ － ／ ＝ ∧ ∠ ∩ ∪ ° ÷ ≡ ≥ ∞ ∫ ≤ ≠ ∨ ‰ ‱ ⊥ π ± √ ∑ ∴ × ¬\n```"
    },
    {
      "id": "s4-36",
      "sectionId": "s4",
      "title": "分数符号",
      "body": "```\n½  ⅓  ⅔  ¼  ¾  ⅕  ⅖  ⅗  ⅘  ⅙  ⅚  ⅐  ⅛  ⅜  ⅝  ⅞  ⅑  ⅒  ↉  ⅟\n```"
    },
    {
      "id": "s4-37",
      "sectionId": "s4",
      "title": "数字符号",
      "body": "```\nⅠ Ⅱ Ⅲ Ⅳ Ⅴ Ⅵ Ⅶ Ⅷ Ⅸ Ⅹ Ⅺ Ⅻ ⅰ ⅱ ⅲ ⅳ ⅴ ⅵ ⅶ ⅷ ⅸ ⅹ ⅺ ⅻ ⓪ ① ② ③ ④ ⑤ ⑥ ⑦ ⑧ ⑨ ⑩ ⓵ ⓶ ⓷ ⓸ ⓹ ⓺ ⓻ ⓼ ⓽ ⓾ ➀ ➁ ➂ ➃ ➄ ➅ ➆ ➇ ➈ ➉ ➊ ➋ ➌ ➍ ➎ ➏ ➐ ➑ ➒ ➓ ⑴ ⑵ ⑶ ⑷⑸ ⑹ ⑺ ⑻ ⑼ ⑽ ⓿ ❶ ❷ ❸ ❹ ❺ ❻ ❼ ❽ ❾ ❿ ㈠ ㈡ ㈢ ㈣ ㈤ ㈥ ㈦ ㈧ ㈨ ㈩ ㊀ ㊁ ㊂ ㊃ ㊄ ㊅ ㊆ ㊇ ㊈ ㊉ ０ １ ２ ３４ ５ ６ ７ ８ ９ \n```"
    },
    {
      "id": "s4-38",
      "sectionId": "s4",
      "title": "单位符号",
      "body": "```\nμ ° ℃ ℉ ㎍ ㎎ ㎏ ℥ ㏌ ㎚ ㎛ ㎜ ㎝ ㎞ ² ³ ㎖ ㎗ ㎘ ㏄ ㏖ ㏒ ㎅ ㎆ ㎇ ㎈ ㎉ ㎐ ㎑ ㎒ ㎓ ㎾ Ω ㏑ ㏈ ㏐ ㏂ ㏘ ㎳ ㎭ ㏅ ㎪ ㏗\n```"
    },
    {
      "id": "s4-39",
      "sectionId": "s4",
      "title": "下标和上标",
      "body": "```\n⁰ ¹ ² ³ ⁴ ⁵ ⁶ ⁷ ⁸ ⁹ ⁺ ⁻ ⁼ ⁽⁾ ⁿ ₀ ₁ ₂ ₃ ₄ ₅ ₆ ₇ ₈ ₉ ₊ ₋ ₌₍ ₎ ₐ ₑ ₒ ₓ ₔ ° ⁱ ⁄\n```"
    },
    {
      "id": "s4-40",
      "sectionId": "s4",
      "title": "PI 符号",
      "body": "```\nΠ π 𝜫 𝝅 𝝥 𝝿 𝞟 𝞹 П п ∏ ϖ ∐ ℼ ㄇ 兀\n```"
    },
    {
      "id": "s5-41",
      "sectionId": "s5",
      "title": "字母字体",
      "body": "```\nⒶ Ⓑ Ⓒ Ⓓ Ⓔ Ⓕ Ⓖ Ⓗ Ⓘ Ⓙ Ⓚ Ⓛ Ⓜ Ⓝ Ⓞ Ⓟ Ⓠ Ⓡ Ⓢ Ⓣ Ⓤ Ⓥ Ⓦ Ⓧ Ⓨ Ⓩ\nⓐ ⓑ ⓒ ⓓ ⓔ ⓕ ⓖ ⓗ ⓘ ⓙ ⓚ ⓛ ⓜ ⓝ ⓞ ⓟ ⓠ ⓡ ⓢ ⓣ ⓤ ⓥ ⓦ ⓧ ⓨ ⓩ \n\nᴀ ʙ ᴄ ᴅ ᴇ ғ ɢ ʜ ɪ ᴊ ᴋ ʟ ᴍ ɴ ᴏ ᴘ ǫ ʀ s ᴛ ᴜ ᴠ ᴡ x ʏ ᴢ\n\n𝓐 𝓑 𝓒 𝓓 𝓔 𝓕 𝓖 𝓗 𝓘 𝓙 𝓚 𝓛 𝓜 𝓝 𝓞 𝓟 𝓠 𝓡 𝓢 𝓣 𝓤 𝓥 𝓦 𝓧 𝓨 𝓩 \n𝓪 𝓫 𝓬 𝓭 𝓮 𝓯 𝓰 𝓱 𝓲 𝓳 𝓴 𝓵 𝓶 𝓷 𝓸 𝓹 𝓺 𝓻 𝓼 𝓽 𝓾 𝓿 𝔀 𝔁 𝔂 𝔃 \n𝒜 ℬ 𝒞 𝒟 ℰ ℱ 𝒢 ℋ ℐ 𝒥 𝒦 ℒ ℳ 𝒩 𝒪 𝒫 𝒬 ℛ 𝒮 𝒯 𝒰 𝒱 𝒲 𝒳 𝒴 𝒵 \n𝒶 𝒷 𝒸 𝒹 𝑒 𝒻 𝑔 𝒽 𝒾 𝒿 𝓀 𝓁 𝓂 𝓃 𝑜 𝓅 𝓆 𝓇 𝓈 𝓉 𝓊 𝓋 𝓌 𝓍 𝓎 𝓏 \n\n🅐 🅑 🅒 🅓 🅔 🅕 🅖 🅗 🅘 🅙 🅚 🅛 🅜 🅝 🅞 🅟 🅠 🅡 🅢 🅣 🅤 🅥 🅦 🅧 🅨 🅩\n\n𝔸 𝔹 ℂ 𝔻 𝔼 𝔽 𝔾 ℍ 𝕀 𝕁 𝕂 𝕃 𝕄 ℕ 𝕆 ℙ ℚ ℝ 𝕊 𝕋 𝕌 𝕍 𝕎 𝕏 𝕐 ℤ\n𝕒 𝕓 𝕔 𝕕 𝕖 𝕗 𝕘 𝕙 𝕚 𝕛 𝕜 𝕝 𝕞 𝕟 𝕠 𝕡 𝕢 𝕣 𝕤 𝕥 𝕦 𝕧 𝕨 𝕩 𝕪 𝕫\n\n🄰 🄱 🄲 🄳 🄴 🄵 🄶 🄷 🄸 🄹 🄺 🄻 🄼 🄽 🄾 🄿 🅀 🅁 🅂 🅃 🅄 🅅 🅆 🅇 🅈 🅉 \n\n🅰 🅱 🅲 🅳 🅴 🅵 🅶 🅷 🅸 🅹 🅺 🅻 🅼 🅽 🅾 🅿 🆀 🆁 🆂 🆃 🆄 🆅 🆆 🆇 🆈 🆉\n\n𝕬 𝕭 𝕮 𝕯 𝕰 𝕱 𝕲 𝕳 𝕴 𝕵 𝕶 𝕷 𝕸 𝕹 𝕺 𝕻 𝕼 𝕽 𝕾 𝕿 𝖀 𝖁 𝖂 𝖃 𝖄 𝖅\n𝖆 𝖇 𝖈 𝖉 𝖊 𝖋 𝖌 𝖍 𝖎 𝖏 𝖐 𝖑 𝖒 𝖓 𝖔 𝖕 𝖖 𝖗 𝖘 𝖙 𝖚 𝖛 𝖜 𝖝 𝖞 𝖟\n𝔄 𝔅 ℭ 𝔇 𝔈 𝔉 𝔊 ℌ ℑ 𝔍 𝔎 𝔏 𝔐 𝔑 𝔒 𝔓 𝔔 ℜ 𝔖 𝔗 𝔘 𝔙 𝔚 𝔛 𝔜 ℨ\n𝔞 𝔟 𝔠 𝔡 𝔢 𝔣 𝔤 𝔥 𝔦 𝔧 𝔨 𝔩 𝔪 𝔫 𝔬 𝔭 𝔮 𝔯 𝔰 𝔱 𝔲 𝔳 𝔴 𝔵 𝔶 𝔷\n\n𝐀 𝐁 𝐂 𝐃 𝐄 𝐅 𝐆 𝐇 𝐈 𝐉 𝐊 𝐋 𝐌 𝐍 𝐎 𝐏 𝐐 𝐑 𝐒 𝐓 𝐔 𝐕 𝐖 𝐗 𝐘 𝐙\n𝐚 𝐛 𝐜 𝐝 𝐞 𝐟 𝐠 𝐡 𝐢 𝐣 𝐤 𝐥 𝐦 𝐧 𝐨 𝐩 𝐪 𝐫 𝐬 𝐭 𝐮 𝐯 𝐰 𝐱 𝐲 𝐳 \n\n𝘈 𝘉 𝘊 𝘋 𝘌 𝘍 𝘎 𝘏 𝘐 𝘑 𝘒 𝘓 𝘔 𝘕 𝘖 𝘗 𝘘 𝘙 𝘚 𝘛 𝘜 𝘝 𝘞 𝘟 𝘠 𝘡\n𝘢 𝘣 𝘤 𝘥 𝘦 𝘧 𝘨 𝘩 𝘪 𝘫 𝘬 𝘭 𝘮 𝘯 𝘰 𝘱 𝘲 𝘳 𝘴 𝘵 𝘶 𝘷 𝘸 𝘹 𝘺 𝘻\n𝘼 𝘽 𝘾 𝘿 𝙀 𝙁 𝙂 𝙃 𝙄 𝙅 𝙆 𝙇 𝙈 𝙉 𝙊 𝙋 𝙌 𝙍 𝙎 𝙏 𝙐 𝙑 𝙒 𝙓 𝙔 𝙕\n𝙖 𝙗 𝙘 𝙙 𝙚 𝙛 𝙜 𝙝 𝙞 𝙟 𝙠 𝙡 𝙢 𝙣 𝙤 𝙥 𝙦 𝙧 𝙨 𝙩 𝙪 𝙫 𝙬 𝙭 𝙮 𝙯\n```"
    },
    {
      "id": "s5-42",
      "sectionId": "s5",
      "title": "希腊符号",
      "body": "```\nΑ Β Γ Δ Ε Ζ Η Θ Ι Κ Λ Μ Ν Ξ Ο Π Ρ Σ Τ Υ Φ Χ Ψ Ω α β γ δ ε ζ η θ ι κ λ μ ν ξ ο π ρ ς σ τ υ φ χ ψ ω\n```"
    },
    {
      "id": "s5-43",
      "sectionId": "s5",
      "title": "拉丁字母",
      "body": "```\nÆ Á Â Â À Å Ã Ä Ç Ð É Ê È Ë Í Î Ì Ï Ñ Ó Ô Ò Ø Õ Ö Þ Ú Û Ù Ü Ý á â æ à å ã ä ç é ê è ð ë í î ì ïñ ó ô ò ø õ ö ß þ ú û ù ü ý ÿ\n```"
    },
    {
      "id": "s5-44",
      "sectionId": "s5",
      "title": "拉丁扩展字符",
      "body": "```\nĀ ā Ă ă Ą ą Ć ć Ĉ ĉ Ċ ċ Č č Ď ď Đ đ Ē ē Ĕ ĕ Ė ė Ę ę Ě ě Ĝ ĝ Ğ ğ Ġ ġ Ģ ģ Ĥ ĥ Ħ ħ Ĩ ĩ Ī ī Ĭ ĭ Į į İ ı Ĳ ĳ Ĵ ĵ Ķ ķ ĸ Ĺ ĺ Ļ ļ Ľ ľ Ŀ ŀ Ł ł Ń ń Ņ ņ Ň ň Ŋ ŋ Ō ō Ŏ ŏ Ő ő Œ œ Ŕ ŕ Ŗ ŗ Ř ř Ś ś Ŝ ŝ Ş ş Š š Ţ ţ Ť ť Ŧ ŧ Ũ ũ Ū ū Ŭ ŭ Ů ů Ű ű Ų ų Ŵ ŵ Ŷ ŷ Ÿ Ź źŻ ż Ž ž ſ ŉ\n```"
    },
    {
      "id": "s5-45",
      "sectionId": "s5",
      "title": "中国符号",
      "body": "```\n㊊ ㊋ ㊌ ㊍ ㊎ ㊏ ㊐ ㊑ ㊒ ㊓ ㊔ ㊕ ㊖ ㊗ ㊘ ㊙ ㊚ ㊛ ㊜ ㊝ ㊞ ㊟ ㊠ ㊡ ㊢ ㊣ ㊤ ㊥ ㊦ ㊧ ㊨ ㊩ ㊪ ㊫ ㊬ ㊭ ㊮ ㊯ ㊰\n```"
    },
    {
      "id": "s5-46",
      "sectionId": "s5",
      "title": "拼音注音",
      "body": "```\nā  á  ǎ  à  ō  ó  ǒ  ò  ē  é ě  è  ń  ň    ī  í  ǐ  ì  ū ú  ǔ  ù  ǖ  ǘ  ǚ  ǜ  ü  ɑ  \n```"
    },
    {
      "id": "s5-47",
      "sectionId": "s5",
      "title": "俄文字符",
      "body": "```\nА  Б  В  Г  Д  Е  Ё  Ж  З  И Й  К  Л  М  Н  О  П  Р  С  Т У  Ф  Х  Ц  Ч  Ш  Щ  Ъ  Ы  Ь Э  Ю  Я а  б  в  г  д  е  ё  ж  з  и й  к  л  м  н  о  п  р  с  т у  ф  х  ц  ч  ш  щ  ъ  ы  ь э  ю  я\n```"
    },
    {
      "id": "s5-48",
      "sectionId": "s5",
      "title": "日文字符",
      "body": "```\nぁ あ ぃ い ぅ う ぇ え ぉ お か が き ぎ く ぐ け げ こ ご さ ざ し じ す ず せ ぜ そ ぞ た だ ち ぢ っ つ づ て で と ど な に ぬ ね の は ば ぱ ひ び ぴ ふ ぶ ぷ へ べ ぺ ほ ぼ ぽ ま み む め も ゃ や ゅ ゆ ょ よ ら り る れ ろ ゎ わ ゐ ゑ を ん ゔ ゕ ゖ゚ ゛ ゜ ゝ ゞ ゟ ゠ ァ ア ィ イ ゥ ウ ェ エ ォ オ カ ガ キ ギ ク グ ケ ゲ コ ゴ サ ザ シ ジ ス ズ セ ゼ ソ ゾ タ ダ チ ヂ ッ ツ ヅ テ デ ト ド ナ ニ ヌ ネ ノ ハ バ パ ヒ ビ ピ フ ブ プ ヘ ベ ペ ホ ボ ポ マ ミ ム メ モ ャ ヤ ュ ユ ョ ヨ ラ リ ル レ ロ ヮ ワ ヰ ヱ ヲ ン ヴ ヵ ヶ ヷ ヸ ヹ ヺ ・ ー ヽ ヾ ヿ ㍐ ㍿\n```"
    },
    {
      "id": "s5-49",
      "sectionId": "s5",
      "title": "韩国符号",
      "body": "```\nㄱ ㄲ ㄳ ㄴ ㄵ ㄶ ㄷ ㄸ ㄹ ㄺ ㄻ ㄼ ㄽ ㄾ ㄿ ㅀ ㅁ ㅂ ㅃ ㅄ ㅅ ㅆ ㅇ ㅈ ㅉ ㅊ ㅋ ㅌ ㅍ ㅎ ㅏ ㅐ ㅑ ㅒ ㅓ ㅔ ㅕ ㅖ ㅗ ㅘ ㅙ ㅚ ㅛ ㅜ ㅝ ㅞ ㅟ ㅠ ㅡ ㅢ ㅥ ㅦ ㅧ ㅨ ㅩ ㅪ ㅫ ㅬ ㅭ ㅮ ㅯ ㅰ ㅱ ㅲ ㅳ ㅴ ㅵ ㅶ ㅷ ㅸ ㅹ ㅺ ㅻ ㅼ ㅽ ㅾ ㅿ ㆀ ㆁ ㆂ ㆃ ㆄ ㆅ ㆆ ㆇ ㆈ ㆉ ㆊ\n```"
    },
    {
      "id": "s5-50",
      "sectionId": "s5",
      "title": "标点符号",
      "body": "```\n˙ ‥ ‧ ‵ 、 。 ﹐ ﹒ ﹔ ﹕ ！ ＃ ＄ ％ ＆ ＊ ， ． ： ； ？ ＠ ～ • … · . ᐟ ¡ ¿ ¦ ¨ ¯ ´ · ¸ º ‽ ‼ ⁏ ※ † ‡ ˉ ˘ ⁇ ⁈ ⁉ ˆ ⁊ ⸘\n```"
    },
    {
      "id": "s5-51",
      "sectionId": "s5",
      "title": "日本时代名称",
      "body": "```\n㋿ ㍻ ㍼ ㍽ ㍾ \n```"
    },
    {
      "id": "s5-52",
      "sectionId": "s5",
      "title": "括号符号",
      "body": "```\n〈 〉 《 》 「 」 『 』 【 】 〔 〕 ︵ ︶ ︷ ︸ ︹ ︺ ︻ ︼ ︽ ︾ ︿ ﹀ ﹁ ﹂ ﹃ ﹄﹙ ﹚ ﹛ ﹜ ﹝ ﹞ ﹤ ﹥ （ ） ＜ ＞｛ ｝ ❬ ❭ ❮ ❯ ❰ ❱ 〖 〗 〘 〙 〚 〛 ⟨ ⟩ ‹ › « » ｢ ｣ ⌃ ⌄ ⌵\n```"
    },
    {
      "id": "s5-53",
      "sectionId": "s5",
      "title": "%E5%BC%95%E5%8F%B7",
      "body": "%60%60%60%0A%22%20'%20%C2%AB%20%C2%BB%20%E2%80%98%20%E2%80%99%20%E2%80%9A%20%E2%80%9B%20%E2%80%9C%20%E2%80%9D%20%E2%80%9E%20%E2%80%9F%20%E2%80%B9%20%E2%80%BA%20%E2%9D%9B%20%E2%9D%9C%20%E2%9D%9D%20%E2%9D%9E%20%E3%80%9D%20%E3%80%9E%20%E3%80%9F%20%E3%80%83%20%EF%BC%82%20%EF%BC%87%20%E2%80%B2%20%E2%80%B3%20%60%20%CB%8A%20%E2%80%95%20%E2%80%94%20%E2%80%93%0A%60%60%60",
      "encoded": true
    },
    {
      "id": "s5-54",
      "sectionId": "s5",
      "title": "段落标记",
      "body": "```\n§ ¶ ❡ ⁋ ※\n```"
    },
    {
      "id": "s6-55",
      "sectionId": "s6",
      "title": "另见",
      "body": "• [特殊符号](https://cn.piliapp.com/symbol/) _(piliapp.com)_"
    }
  ],
  "source": {
    "repo": "https://github.com/jaywcjlove/reference",
    "path": "docs/symbol-code.md",
    "ref": "main",
    "url": "https://github.com/jaywcjlove/reference/tree/main/docs/symbol-code.md",
    "lang": "zh",
    "mode": "local"
  }
}